mpgameserver/__init__.py
mpgameserver/__main__.py
mpgameserver/auth.py
mpgameserver/captcha.py
mpgameserver/client.py
mpgameserver/connection.py
mpgameserver/context.py
mpgameserver/crypto.py
mpgameserver/dispatch.py
mpgameserver/graph.py
mpgameserver/guiserver.py
mpgameserver/handler.py
mpgameserver/http_client.py
mpgameserver/http_server.py
mpgameserver/logger.py
mpgameserver/serializable.py
mpgameserver/server.py
mpgameserver/task.py
mpgameserver/timer.py
mpgameserver/twisted.py
mpgameserver/util.py
mpgameserver/pylon/__init__.py
mpgameserver/pylon/engine.py
mpgameserver/pylon/tilesheet.py
mpgameserver-0.2.4.dist-info/LICENSE
mpgameserver-0.2.4.dist-info/METADATA
mpgameserver-0.2.4.dist-info/WHEEL
mpgameserver-0.2.4.dist-info/entry_points.txt
mpgameserver-0.2.4.dist-info/top_level.txt
mpgameserver-0.2.4.dist-info/RECORD
