Metadata-Version: 2.1
Name: mpgameserver
Version: 0.2.4
Summary: Python Multiplayer Game Server
Author-email: Nick Setzer <nsetzer@users.noreply.github.com>
Keywords: PYGAME,MULTIPLAYER,UDP,SERVER
Requires-Python: >=3.8
License-File: LICENSE
Requires-Dist: twisted >=24.3.0
Requires-Dist: pyOpenSSL >=24.1.0
Requires-Dist: service-identity >=24.1.0
Requires-Dist: cryptography >=42.0.7
Provides-Extra: dev
Requires-Dist: grip >=4.5.2 ; extra == 'dev'
Requires-Dist: coverage >=5.3 ; extra == 'dev'
Provides-Extra: pygame
Requires-Dist: pygame >=2.5.2 ; extra == 'pygame'
Requires-Dist: pillow >=10.3.0 ; extra == 'pygame'
